{"Sections": {"Q": {"conflictingsections": [], "dectrig": [["A2", "upcount"]], "description": "Between level crossing and 47", "homesignal": [], "inctrig": [["A1", "upcount"]], "mode": 1, "occstatus": 0, "ref": "Q", "routestatus": ""}, "R": {"conflictingsections": [], "dectrig": [["A3", "upcount"]], "description": "Between 47 and 48", "homesignal": ["47"], "inctrig": [["A2", "upcount"]], "mode": 0, "occstatus": 0, "ref": "R", "routestatus": ""}, "S": {"conflictingsections": [], "dectrig": [], "description": "Temp section for all platforms", "homesignal": ["48"], "inctrig": [["A3", "upcount"]], "mode": 0, "occstatus": 0, "ref": "S", "routestatus": ""}}, "AxleCounters": {"A1": {"address": 1, "description": "After Level Crossing", "downcount": 0, "mode": 0, "ref": "A1", "upcount": 0}, "A2": {"address": 2, "description": "At 47 Signal", "downcount": 0, "mode": 0, "ref": "A2", "upcount": 0}, "A3": {"address": 3, "description": "At 48 Signal", "downcount": 0, "mode": 0, "ref": "A3", "upcount": 0}}, "Signals": {"47": {"address": "32", "aspect": "0", "availableaspects": 0, "bannerreg": 0, "callingonreg": 0, "cautionreg": 0, "clearreg": 1, "dangerreg": 0, "description": "Platform home signal", "directionindicator": 0, "illumination": "On", "ref": "47", "route1reg": 0, "route2reg": 0, "route3reg": 0, "route4reg": 0, "route5reg": 0, "route6reg": 0, "sigtype": 0}, "48": {"address": "31", "aspect": "0", "availableaspects": 0, "bannerreg": 0, "callingonreg": 0, "cautionreg": 0, "clearreg": 0, "dangerreg": 0, "description": "Platform home signal", "directionindicator": 0, "illumination": "On", "ref": "48", "route1reg": 0, "route2reg": 0, "route3reg": 0, "route4reg": 0, "route5reg": 0, "route6reg": 0, "sigtype": 1}}, "Plungers": {"P1": {"address": 21, "description": "Select Platform 2", "mode": 1, "ref": "P1", "register": 0, "status": 0}, "P2": {"address": 21, "description": "Select Platform 3", "mode": 1, "ref": "P2", "register": 1, "status": 0}, "P5": {"address": 21, "description": "Select Platform 4", "mode": 1, "ref": "P5", "register": 3, "status": 0}, "P3": {"address": 23, "description": "Exit Platform 4", "mode": 1, "ref": "P3", "register": 0, "status": 0}, "P4": {"address": 22, "description": "Cycle Route", "mode": 1, "ref": "P4", "register": 0, "status": 0}, "P6": {"address": 21, "description": "Exit Yard", "mode": 1, "ref": "P6", "register": 7, "status": 0}}, "Points": {"100": {"address": "51", "description": "Points Platform 2/3", "detection": "", "mode": 1, "ref": "100", "setstatus": ""}, "300": {"address": "52", "description": "Points Platform 3/4", "detection": "", "mode": 1, "ref": "300", "setstatus": ""}}, "Routes": {"gg": {"description": "gggg", "mode": 0, "points": [0], "priority": 1, "ref": "gg", "sections": [0, 1], "signals": [1], "trigger": []}}}